djeasyview/__init__.py
djeasyview/exceptions.py
djeasyview/response.py
djeasyview/serializers.py
djeasyview/utils.py
djeasyview/views.py
djeasyview-1.0.15.dist-info/LICENSE
djeasyview-1.0.15.dist-info/METADATA
djeasyview-1.0.15.dist-info/WHEEL
djeasyview-1.0.15.dist-info/top_level.txt
djeasyview-1.0.15.dist-info/RECORD
