Metadata-Version: 2.1
Name: djeasyview
Version: 1.0.15
Author: Anand Raj
Author-email: anand98.ar@gmail.com
License: MIT
Classifier: Development Status :: 5 - Production/Stable
Classifier: Intended Audience :: Education
Classifier: Operating System :: Microsoft :: Windows :: Windows 10
Classifier: Programming Language :: Python :: 3
Requires-Python: >=3.8
License-File: LICENSE
Requires-Dist: django
Requires-Dist: djangorestframework
